{
  "@context": "/contexts/Card",
  "@id": "/cards/ALT_ALIZE_A_BR_37_R2",
  "@type": "Card",
  "loreEntries": [
    {
      "@id": "/lore_entries/2VC7W0157M87TAZJ1NZC0CDRRF",
      "@type": "LoreEntry",
      "loreEntryElements": [
        {
          "@id": "/lore_entry_elements/01J3JJGM1PQBY9HMJRBE6YRAKS",
          "@type": "LoreEntryElement",
          "loreEntryElementType": {
            "@id": "/lore_entry_element_types/01GR6AENPX6HQP8G16KNV7BNA2",
            "@type": "LoreEntryElementType",
            "id": "01GR6AENPX6HQP8G16KNV7BNA2",
            "reference": "FLAVOR_TEXT",
            "subject": "Flavor Text"
          },
          "id": "01J3JJGM1PQBY9HMJRBE6YRAKS",
          "text": "« Ce qui ne te tue pas te rend plus fort. »"
        },
        {
          "@id": "/lore_entry_elements/01JVYNABYJKTATXBFP1WQRFDBT",
          "@type": "LoreEntryElement",
          "loreEntryElementType": {
            "@id": "/lore_entry_element_types/01GR6AE2ZSVVYP6SDJXN8Q5DVF",
            "@type": "LoreEntryElementType",
            "id": "01GR6AE2ZSVVYP6SDJXN8Q5DVF",
            "reference": "STORY",
            "subject": "Histoire"
          },
          "id": "01JVYNABYJKTATXBFP1WQRFDBT",
          "text": ""
        },
        {
          "@id": "/lore_entry_elements/01JVYNABY85V1CY84Q35AEK94A",
          "@type": "LoreEntryElement",
          "loreEntryElementType": {
            "@id": "/lore_entry_element_types/01GR6AFCC93PF6T4EYVTXXYJY9",
            "@type": "LoreEntryElementType",
            "id": "01GR6AFCC93PF6T4EYVTXXYJY9",
            "reference": "INSPIRATION",
            "subject": "Inspiration"
          },
          "id": "01JVYNABY85V1CY84Q35AEK94A",
          "text": ""
        },
        {
          "@id": "/lore_entry_elements/01JVYNABXPWBK94WF65PPYDCQ2",
          "@type": "LoreEntryElement",
          "loreEntryElementType": {
            "@id": "/lore_entry_element_types/01H19024M31D80P12EJCYX9GB0",
            "@type": "LoreEntryElementType",
            "id": "01H19024M31D80P12EJCYX9GB0",
            "reference": "NARRATOR",
            "subject": "Narré par"
          },
          "id": "01JVYNABXPWBK94WF65PPYDCQ2",
          "text": ""
        },
        {
          "@id": "/lore_entry_elements/01JVYNABXX61Y2EP7VP5PFC3HS",
          "@type": "LoreEntryElement",
          "loreEntryElementType": {
            "@id": "/lore_entry_element_types/01GS7V4ZMD4F2Q0EVQ2GSSJHE2",
            "@type": "LoreEntryElementType",
            "id": "01GS7V4ZMD4F2Q0EVQ2GSSJHE2",
            "reference": "DATE",
            "subject": "Date"
          },
          "id": "01JVYNABXX61Y2EP7VP5PFC3HS",
          "text": ""
        }
      ],
      "loreEntryType": {
        "@id": "/lore_entry_types/01HNGY4YPR0FVZVYWD8YFE0PHP",
        "@type": "LoreEntryType",
        "id": "01HNGY4YPR0FVZVYWD8YFE0PHP",
        "reference": "CHARACTER",
        "name": "Character",
        "description": ""
      },
      "id": "2VC7W0157M87TAZJ1NZC0CDRRF",
      "reference": "ALT_ALIZE_A_BR_37_C"
    }
  ],
  "cardType": {
    "@id": "/card_types/01H19NWA92A4ERAC4ATMSZNASS",
    "@type": "CardType",
    "reference": "CHARACTER",
    "id": "01H19NWA92A4ERAC4ATMSZNASS",
    "name": "Personnage"
  },
  "cardSubTypes": [
    {
      "@type": "CardSubType",
      "@id": "/.well-known/genid/6397c14722ed9d75fc89",
      "reference": "ADVENTURER",
      "id": "01HKAGPC92CGHANVSRSC8R8ES6",
      "name": "Aventurier"
    }
  ],
  "cardSet": {
    "@id": "/card_sets/ALIZE",
    "@type": "CardSet",
    "id": "01J1Q4NZCDCGMFTFKASM8H29N6",
    "reference": "ALIZE",
    "name": "Épreuve du froid"
  },
  "rarity": {
    "@type": "Rarity",
    "@id": "/.well-known/genid/18309abffb79538d010f",
    "reference": "RARE",
    "id": "01GE7AC9WY6PK56RADXXD6P1T5",
    "name": "Rare"
  },
  "cardRulings": [],
  "imagePath": "https://altered-prod-eu.s3.amazonaws.com/Art/ALIZE/CARDS/ALT_ALIZE_A_BR_37/JPG/fr_FR/5b0f8ec6fe96d76a820c435520683812.jpg",
  "assets": {
    "WEB": [
      "https://altered-prod-eu.s3.amazonaws.com/Art/ALIZE/CARDS/ALT_ALIZE_A_BR_37/WEB_3d00216d0ed0cbdde307af3590b55dca",
      "https://altered-prod-eu.s3.amazonaws.com/Art/ALIZE/CARDS/ALT_ALIZE_A_BR_37/WEB_20599b71ed48f0778f89a7e61d817f29",
      "https://altered-prod-eu.s3.amazonaws.com/Art/ALIZE/CARDS/ALT_ALIZE_A_BR_37/WEB_d7e30df8414ad334bd1990f62f9a8878"
    ]
  },
  "lowerPrice": 0,
  "qrUrlDetail": "https://qr.altered.gg/ALT_ALIZE_A_BR_37_R2",
  "reference": "ALT_ALIZE_A_BR_37_R2",
  "id": "01J3GR3VQNGC7DEGP8XMFY66WC",
  "mainFaction": {
    "@id": "/factions/LY",
    "@type": "Faction",
    "reference": "LY",
    "color": "#cf4171",
    "id": "01GE7AC9XGB6JE2V63WXWN4FB3",
    "name": "Lyra"
  },
  "allImagePath": {
    "fr-fr": "https://altered-prod-eu.s3.amazonaws.com/Art/ALIZE/CARDS/ALT_ALIZE_A_BR_37/JPG/fr_FR/5b0f8ec6fe96d76a820c435520683812.jpg",
    "en-us": "https://altered-prod-eu.s3.amazonaws.com/Art/ALIZE/CARDS/ALT_ALIZE_A_BR_37/JPG/en_US/776e76cfa8bd0e73c321bfd220b36900.jpg",
    "de-de": "https://altered-prod-eu.s3.amazonaws.com/Art/ALIZE/CARDS/ALT_ALIZE_A_BR_37/JPG/de_DE/e62ba0413f776c4fb8aac97438249df8.jpg",
    "it-it": "https://altered-prod-eu.s3.amazonaws.com/Art/ALIZE/CARDS/ALT_ALIZE_A_BR_37/JPG/it_IT/8a03d0ab7069c4782513f74482c7f8d8.jpg",
    "es-es": "https://altered-prod-eu.s3.amazonaws.com/Art/ALIZE/CARDS/ALT_ALIZE_A_BR_37/JPG/es_ES/c5921c911d119a80aa3003335fdfccad.jpg"
  },
  "name": "Gericht, Bretteur Honoré",
  "elements": {
    "MAIN_COST": "3",
    "RECALL_COST": "4",
    "OCEAN_POWER": "3",
    "FOREST_POWER": "3",
    "MOUNTAIN_POWER": "3",
    "MAIN_EFFECT": "#Si je devais gagner [[Fugace]], je gagne 1 boost à la place.#"
  },
  "isSuspended": false,
  "isErrated": false,
  "isBanned": false,
  "collectorNumber": "TBF-025-F-FR"
}