{
  "@context": "/contexts/Card",
  "@id": "/cards/ALT_ALIZE_B_OR_42_C",
  "@type": "Card",
  "loreEntries": [
    {
      "@id": "/lore_entries/2YXS7EEVAW96XR2EPJBVY7HE9H",
      "@type": "LoreEntry",
      "loreEntryElements": [
        {
          "@id": "/lore_entry_elements/01J21J29AVHX5QG82HXZ6JZT07",
          "@type": "LoreEntryElement",
          "loreEntryElementType": {
            "@id": "/lore_entry_element_types/01GR6AENPX6HQP8G16KNV7BNA2",
            "@type": "LoreEntryElementType",
            "id": "01GR6AENPX6HQP8G16KNV7BNA2",
            "reference": "FLAVOR_TEXT",
            "subject": "Flavor Text"
          },
          "id": "01J21J29AVHX5QG82HXZ6JZT07",
          "text": "Do not collect 200 Florets."
        },
        {
          "@id": "/lore_entry_elements/01J21J29BRK7WF7J8EM1QK4XY4",
          "@type": "LoreEntryElement",
          "loreEntryElementType": {
            "@id": "/lore_entry_element_types/01GR6AE2ZSVVYP6SDJXN8Q5DVF",
            "@type": "LoreEntryElementType",
            "id": "01GR6AE2ZSVVYP6SDJXN8Q5DVF",
            "reference": "STORY",
            "subject": "Story"
          },
          "id": "01J21J29BRK7WF7J8EM1QK4XY4",
          "text": "The furious Jinn blocks our path, right in the middle of the narrow pass, which is a charming little patch of greenery that it clearly intends to keep for itself. It melts the snow, determined to wage war on winter all by itself and visibly annoyed by the cold constantly assailing its territory. I feel my men's eyes on my back and sense a bit of challenge in their attitude. I raise an eyebrow. All right, I'll show them what I'm made of. But I'm not going to launch a frontal assault on this walking hibachi – I don't want to ruin my uniform. I cross my arms and look as indifferent as possible, then turn to my troopers, more in jest than in actual defiance. I signal to my new aide-de-camp to bring me my things, and she promptly obeys. Then, like a matador entering the ring, I take a few steps towards the creature.\n\nI write my Glyphs on a piece of paper and calmly charge it with Mana, like an assassin sharpening his blades. Whispers and murmurs sweep through the ranks as bets are placed. Here comes the fun part. I toss the paper onto the ground with a disdainful gesture, like throwing down a gauntlet. There are chuckles and jeers behind me… I turn towards them, flash them an ironic smile, then whip around to shout at the angry Jinn. Naturally, the Eidolon instantly leaps towards me, like an enraged bull rushing at a red cape… and promptly falls into the trap, just as I expected. In a sudden swirl of paper, a cage forms around the flaming Jinn. Behind me comes the sound of cheers, applause and a few disappointed exclamations. Florets are handed from losers to winners as I wave to the crowd. I can't wait to see my score."
        },
        {
          "@id": "/lore_entry_elements/01J21J29B9PBXK8M1ZWQDGWP2B",
          "@type": "LoreEntryElement",
          "loreEntryElementType": {
            "@id": "/lore_entry_element_types/01GR6AFCC93PF6T4EYVTXXYJY9",
            "@type": "LoreEntryElementType",
            "id": "01GR6AFCC93PF6T4EYVTXXYJY9",
            "reference": "INSPIRATION",
            "subject": "Inspiration"
          },
          "id": "01J21J29B9PBXK8M1ZWQDGWP2B",
          "text": ""
        },
        {
          "@id": "/lore_entry_elements/01J21J29968B1472H8FS8DMCW7",
          "@type": "LoreEntryElement",
          "loreEntryElementType": {
            "@id": "/lore_entry_element_types/01H19024M31D80P12EJCYX9GB0",
            "@type": "LoreEntryElementType",
            "id": "01H19024M31D80P12EJCYX9GB0",
            "reference": "NARRATOR",
            "subject": "Narrator"
          },
          "id": "01J21J29968B1472H8FS8DMCW7",
          "text": "SIGISMAR"
        },
        {
          "@id": "/lore_entry_elements/01J21J29ABE9MZ59DQ0K5QN4AK",
          "@type": "LoreEntryElement",
          "loreEntryElementType": {
            "@id": "/lore_entry_element_types/01GS7V4ZMD4F2Q0EVQ2GSSJHE2",
            "@type": "LoreEntryElementType",
            "id": "01GS7V4ZMD4F2Q0EVQ2GSSJHE2",
            "reference": "DATE",
            "subject": "Date"
          },
          "id": "01J21J29ABE9MZ59DQ0K5QN4AK",
          "text": "393 AC"
        }
      ],
      "loreEntryType": {
        "@id": "/lore_entry_types/01HNGY4YWDQJMHNXV999HX7V1P",
        "@type": "LoreEntryType",
        "id": "01HNGY4YWDQJMHNXV999HX7V1P",
        "reference": "SPELL",
        "name": "Spell",
        "description": ""
      },
      "id": "2YXS7EEVAW96XR2EPJBVY7HE9H",
      "reference": "ALT_ALIZE_B_OR_42_C"
    }
  ],
  "cardType": {
    "@id": "/card_types/01GE7AC9X35JXEQZJBBD6E4BKX",
    "@type": "CardType",
    "reference": "SPELL",
    "id": "01GE7AC9X35JXEQZJBBD6E4BKX",
    "name": "Spell"
  },
  "cardSubTypes": [
    {
      "@type": "CardSubType",
      "@id": "/.well-known/genid/2699594fd412dc148267",
      "reference": "DISRUPTION",
      "id": "01HKAGPH80FC347E2P8841D298",
      "name": "Disruption"
    }
  ],
  "cardSet": {
    "@id": "/card_sets/ALIZE",
    "@type": "CardSet",
    "id": "01J1Q4NZCDCGMFTFKASM8H29N6",
    "reference": "ALIZE",
    "name": "Trial by Frost"
  },
  "rarity": {
    "@type": "Rarity",
    "@id": "/.well-known/genid/115f3ab65e7d832c0738",
    "reference": "COMMON",
    "id": "01GE7AC9WEQKW1Y1BF8SCY745A",
    "name": "Common"
  },
  "cardRulings": [
    {
      "@type": "CardRuling",
      "@id": "/.well-known/genid/676045fd268295a80215",
      "eventFormat": "STANDARD",
      "createdAt": "2025-01-31T10:38:20+00:00",
      "question": "Do the boosts of a Character count towards the stat limit?",
      "answer": "Yes."
    }
  ],
  "imagePath": "https://altered-prod-eu.s3.amazonaws.com/Art/ALIZE/CARDS/ALT_ALIZE_B_OR_42/JPG/en_US/d6c030a493cf94d0ae925620b22d8269.jpg",
  "assets": {
    "WEB": [
      "https://altered-prod-eu.s3.amazonaws.com/Art/ALIZE/CARDS/ALT_ALIZE_B_OR_42/WEB_11fb440c7d2027197b70c3d6e7d5371d",
      "https://altered-prod-eu.s3.amazonaws.com/Art/ALIZE/CARDS/ALT_ALIZE_B_OR_42/WEB_d48f47ad302b9170ae3ef91b889013dd"
    ]
  },
  "lowerPrice": 0,
  "qrUrlDetail": "https://qr.altered.gg/ALT_ALIZE_B_OR_42_C",
  "reference": "ALT_ALIZE_B_OR_42_C",
  "id": "01J1Q4P4SN8RYANNFV99ET5V4D",
  "mainFaction": {
    "@id": "/factions/OR",
    "@type": "Faction",
    "reference": "OR",
    "color": "#0f6593",
    "id": "01GE7AC9X78DXSNKNB15KCF69X",
    "name": "Ordis"
  },
  "allImagePath": {
    "de-de": "https://altered-prod-eu.s3.amazonaws.com/Art/ALIZE/CARDS/ALT_ALIZE_B_OR_42/JPG/de_DE/f473094a0a289a15377d76357ba2ce77.jpg",
    "en-us": "https://altered-prod-eu.s3.amazonaws.com/Art/ALIZE/CARDS/ALT_ALIZE_B_OR_42/JPG/en_US/d6c030a493cf94d0ae925620b22d8269.jpg",
    "it-it": "https://altered-prod-eu.s3.amazonaws.com/Art/ALIZE/CARDS/ALT_ALIZE_B_OR_42/JPG/it_IT/b6a6b6adf43f67225c3b626d85281015.jpg",
    "fr-fr": "https://altered-prod-eu.s3.amazonaws.com/Art/ALIZE/CARDS/ALT_ALIZE_B_OR_42/JPG/fr_FR/7b2f5d9c8d2f436e1e78fba1a3f13bab.jpg",
    "es-es": "https://altered-prod-eu.s3.amazonaws.com/Art/ALIZE/CARDS/ALT_ALIZE_B_OR_42/JPG/es_ES/c7e03d5ca964e625a0a01c885c232f49.jpg"
  },
  "name": "Tiny Jail",
  "elements": {
    "MAIN_COST": "2",
    "RECALL_COST": "2",
    "MAIN_EFFECT": "[[Fleeting]].  Send to Reserve target Character with no statistic over 3."
  },
  "isSuspended": false,
  "isErrated": false,
  "isBanned": false,
  "collectorNumber": "TBF-083-C-EN"
}