{
  "@context": "/contexts/Card",
  "@id": "/cards/ALT_BISE_B_LY_58_R1",
  "@type": "Card",
  "loreEntries": [
    {
      "@id": "/lore_entries/45PMPTWZVH8NVA15GANMAAV45R",
      "@type": "LoreEntry",
      "loreEntryElements": [
        {
          "@id": "/lore_entry_elements/01JBT1A670M6EW58BS1QYNVBB1",
          "@type": "LoreEntryElement",
          "loreEntryElementType": {
            "@id": "/lore_entry_element_types/01GR6AENPX6HQP8G16KNV7BNA2",
            "@type": "LoreEntryElementType",
            "id": "01GR6AENPX6HQP8G16KNV7BNA2",
            "reference": "FLAVOR_TEXT",
            "subject": "Flavor Text"
          },
          "id": "01JBT1A670M6EW58BS1QYNVBB1",
          "text": "«¡Papá!». — Sierra"
        },
        {
          "@id": "/lore_entry_elements/01JBT1A68DVJBNMQP96DN1XESY",
          "@type": "LoreEntryElement",
          "loreEntryElementType": {
            "@id": "/lore_entry_element_types/01GR6AE2ZSVVYP6SDJXN8Q5DVF",
            "@type": "LoreEntryElementType",
            "id": "01GR6AE2ZSVVYP6SDJXN8Q5DVF",
            "reference": "STORY",
            "subject": "Story"
          },
          "id": "01JBT1A68DVJBNMQP96DN1XESY",
          "text": "393 AC - I hug him tightly, pressing my wet cheeks and runny nose into his jacket. But he doesn't mind. His arms embrace me and don't seem to want to ever let me go. I feel the fire of Ignescence boiling deep within me, and my soul overflowing with so many emotions that they get scrambled, switch places and battle for expression. Sobs, laughs, dizziness… Memories rise up like bubbles: sudden, uncontrollable, chaotic and blurred: The day the gates were opened, when we said goodbye while fighting back tears; when he held my hand as I was gritting my teeth with impatience to get it all over with, and when he was the only one keeping my head above water; when he came by my workshop, proud of what I'd accomplished with the Axiom, even as he admitted that he didn't fully understand the extent of my fascination…\n\nOddball's slightly jealous beep-beep brings me back to the present, and I grab him so he can share in our hug. Then, as I dry my tears, I look at my father's face, my own blissful face reflected in his glasses. And behind the lenses, I can also make out just a little bit of moisture around the edges of his eyes. Questions crowd my mind. What was he doing here aboard the Wayfarer? Did he come here especially for me? Was he going to stay? Why didn't he tell me he was coming? But I let them all fade away… and I'd never be able to put them into words, anyhow. I'm content to simply look at him, with a slight fear at the back of my mind that this might all be just a dream. But no — he's definitely right here, in the flesh. There's no need to pinch myself. My eyes linger on the little details: the curls of his mustache, his hair with maybe a few more white strands than before… Even though it's only been ten months, I feel like it's been years since I last saw him. And I realize how much I've missed him."
        },
        {
          "@id": "/lore_entry_elements/01JBT1A679NHQ9BSWH3DZSAB8E",
          "@type": "LoreEntryElement",
          "loreEntryElementType": {
            "@id": "/lore_entry_element_types/01GR6AFCC93PF6T4EYVTXXYJY9",
            "@type": "LoreEntryElementType",
            "id": "01GR6AFCC93PF6T4EYVTXXYJY9",
            "reference": "INSPIRATION",
            "subject": "Inspiration"
          },
          "id": "01JBT1A679NHQ9BSWH3DZSAB8E",
          "text": ""
        },
        {
          "@id": "/lore_entry_elements/01JBT1A66FZ3GK4KZH7HCXJ72B",
          "@type": "LoreEntryElement",
          "loreEntryElementType": {
            "@id": "/lore_entry_element_types/01H19024M31D80P12EJCYX9GB0",
            "@type": "LoreEntryElementType",
            "id": "01H19024M31D80P12EJCYX9GB0",
            "reference": "NARRATOR",
            "subject": "Narrator"
          },
          "id": "01JBT1A66FZ3GK4KZH7HCXJ72B",
          "text": "SIERRA"
        },
        {
          "@id": "/lore_entry_elements/01JBT1A66QTBKCGHDS25QKAKNS",
          "@type": "LoreEntryElement",
          "loreEntryElementType": {
            "@id": "/lore_entry_element_types/01GS7V4ZMD4F2Q0EVQ2GSSJHE2",
            "@type": "LoreEntryElementType",
            "id": "01GS7V4ZMD4F2Q0EVQ2GSSJHE2",
            "reference": "DATE",
            "subject": "Date"
          },
          "id": "01JBT1A66QTBKCGHDS25QKAKNS",
          "text": ""
        }
      ],
      "loreEntryType": {
        "@id": "/lore_entry_types/01HNGY4YWDQJMHNXV999HX7V1P",
        "@type": "LoreEntryType",
        "id": "01HNGY4YWDQJMHNXV999HX7V1P",
        "reference": "SPELL",
        "name": "Spell",
        "description": ""
      },
      "id": "45PMPTWZVH8NVA15GANMAAV45R",
      "reference": "ALT_BISE_B_LY_58_C"
    }
  ],
  "cardType": {
    "@id": "/card_types/01GE7AC9X35JXEQZJBBD6E4BKX",
    "@type": "CardType",
    "reference": "SPELL",
    "id": "01GE7AC9X35JXEQZJBBD6E4BKX",
    "name": "Hechizo"
  },
  "cardSubTypes": [
    {
      "@type": "CardSubType",
      "@id": "/.well-known/genid/f6ed49fa76f0a1aeaebc",
      "reference": "CONJURATION",
      "id": "01HKAGQJMGEVS21MCGWDGG8KW0",
      "name": "Conjuro"
    }
  ],
  "cardSet": {
    "@id": "/card_sets/BISE",
    "@type": "CardSet",
    "id": "01JB1YGHBNB4YP1VYJY12XCKJN",
    "reference": "BISE",
    "name": "Whispers from the Maze"
  },
  "rarity": {
    "@type": "Rarity",
    "@id": "/.well-known/genid/9e267a598c50f8bdb5f5",
    "reference": "RARE",
    "id": "01GE7AC9WY6PK56RADXXD6P1T5",
    "name": "Rare"
  },
  "cardRulings": [],
  "imagePath": "https://altered-prod-eu.s3.amazonaws.com/Art/BISE/CARDS/ALT_BISE_B_LY_58/JPG/es_ES/4f32e6724598c50721d9c05acea0b3b3.jpg",
  "assets": {
    "WEB": [
      "https://altered-prod-eu.s3.amazonaws.com/Art/BISE/CARDS/ALT_BISE_B_LY_58/WEB_2a1e8f549d9eca20c75025f1fb8afbe4",
      "https://altered-prod-eu.s3.amazonaws.com/Art/BISE/CARDS/ALT_BISE_B_LY_58/WEB_4db133caecb4e302d7ee9e44adbfdbd0"
    ]
  },
  "lowerPrice": 0,
  "qrUrlDetail": "https://qr.altered.gg/ALT_BISE_B_LY_58_R1",
  "reference": "ALT_BISE_B_LY_58_R1",
  "id": "01JB1YGPBJ75ART9E9GCVPSPWY",
  "mainFaction": {
    "@id": "/factions/LY",
    "@type": "Faction",
    "reference": "LY",
    "color": "#cf4171",
    "id": "01GE7AC9XGB6JE2V63WXWN4FB3",
    "name": "Lyra"
  },
  "allImagePath": {
    "de-de": "https://altered-prod-eu.s3.amazonaws.com/Art/BISE/CARDS/ALT_BISE_B_LY_58/JPG/de_DE/4760b1859aef4a510902cb7e36906dc6.jpg",
    "it-it": "https://altered-prod-eu.s3.amazonaws.com/Art/BISE/CARDS/ALT_BISE_B_LY_58/JPG/it_IT/b26b1292cf6986f4592cabcccb1e9697.jpg",
    "es-es": "https://altered-prod-eu.s3.amazonaws.com/Art/BISE/CARDS/ALT_BISE_B_LY_58/JPG/es_ES/4f32e6724598c50721d9c05acea0b3b3.jpg",
    "fr-fr": "https://altered-prod-eu.s3.amazonaws.com/Art/BISE/CARDS/ALT_BISE_B_LY_58/JPG/fr_FR/24da4043a6326e8ce8477c7d3c5d6fac.jpg",
    "en-us": "https://altered-prod-eu.s3.amazonaws.com/Art/BISE/CARDS/ALT_BISE_B_LY_58/JPG/en_US/c5064e699f7831760733b67103f49e37.jpg"
  },
  "name": "Reencuentro feliz",
  "elements": {
    "MAIN_COST": "2",
    "RECALL_COST": "#1#",
    "MAIN_EFFECT": "#[Recuperación].# (Si voy a la reserva después de que se resuelva mi efecto, agótame {T}. Las cartas agotadas no se pueden jugar y no tienen habilidades de apoyo.)  [Reabastece]. Si colocas un personaje en reserva de esta manera, luego puedes #colocarlo en tu mano.#"
  },
  "isSuspended": false,
  "isErrated": false,
  "isBanned": false,
  "collectorNumber": "WFM-046-R-ES"
}